odoo/addons/stock_lock_lot/README.rst
odoo/addons/stock_lock_lot/__init__.py
odoo/addons/stock_lock_lot/__manifest__.py
odoo/addons/stock_lock_lot/data/stock_lock_lot_data.xml
odoo/addons/stock_lock_lot/i18n/am.po
odoo/addons/stock_lock_lot/i18n/ar.po
odoo/addons/stock_lock_lot/i18n/bg.po
odoo/addons/stock_lock_lot/i18n/bs.po
odoo/addons/stock_lock_lot/i18n/ca.po
odoo/addons/stock_lock_lot/i18n/ca_ES.po
odoo/addons/stock_lock_lot/i18n/cs.po
odoo/addons/stock_lock_lot/i18n/da.po
odoo/addons/stock_lock_lot/i18n/de.po
odoo/addons/stock_lock_lot/i18n/el_GR.po
odoo/addons/stock_lock_lot/i18n/en_AU.po
odoo/addons/stock_lock_lot/i18n/en_GB.po
odoo/addons/stock_lock_lot/i18n/es.po
odoo/addons/stock_lock_lot/i18n/es_AR.po
odoo/addons/stock_lock_lot/i18n/es_CL.po
odoo/addons/stock_lock_lot/i18n/es_CO.po
odoo/addons/stock_lock_lot/i18n/es_CR.po
odoo/addons/stock_lock_lot/i18n/es_DO.po
odoo/addons/stock_lock_lot/i18n/es_EC.po
odoo/addons/stock_lock_lot/i18n/es_ES.po
odoo/addons/stock_lock_lot/i18n/es_MX.po
odoo/addons/stock_lock_lot/i18n/es_PE.po
odoo/addons/stock_lock_lot/i18n/es_PY.po
odoo/addons/stock_lock_lot/i18n/es_VE.po
odoo/addons/stock_lock_lot/i18n/et.po
odoo/addons/stock_lock_lot/i18n/eu.po
odoo/addons/stock_lock_lot/i18n/fa.po
odoo/addons/stock_lock_lot/i18n/fi.po
odoo/addons/stock_lock_lot/i18n/fr.po
odoo/addons/stock_lock_lot/i18n/fr_CA.po
odoo/addons/stock_lock_lot/i18n/fr_CH.po
odoo/addons/stock_lock_lot/i18n/fr_FR.po
odoo/addons/stock_lock_lot/i18n/gl.po
odoo/addons/stock_lock_lot/i18n/gl_ES.po
odoo/addons/stock_lock_lot/i18n/he.po
odoo/addons/stock_lock_lot/i18n/hi.po
odoo/addons/stock_lock_lot/i18n/hr.po
odoo/addons/stock_lock_lot/i18n/hr_HR.po
odoo/addons/stock_lock_lot/i18n/hu.po
odoo/addons/stock_lock_lot/i18n/id.po
odoo/addons/stock_lock_lot/i18n/it.po
odoo/addons/stock_lock_lot/i18n/ja.po
odoo/addons/stock_lock_lot/i18n/ko.po
odoo/addons/stock_lock_lot/i18n/lo.po
odoo/addons/stock_lock_lot/i18n/lt.po
odoo/addons/stock_lock_lot/i18n/lt_LT.po
odoo14_addon_stock_lock_lot-14.0.1.0.1.dev15.dist-info/METADATA
odoo14_addon_stock_lock_lot-14.0.1.0.1.dev15.dist-info/WHEEL
odoo14_addon_stock_lock_lot-14.0.1.0.1.dev15.dist-info/top_level.txt
odoo14_addon_stock_lock_lot-14.0.1.0.1.dev15.dist-info/RECORD
